INILibrary/__init__.py
INILibrary/INILibrary.py
robotframework_inilibrary-1.0.4.dist-info/METADATA
robotframework_inilibrary-1.0.4.dist-info/WHEEL
robotframework_inilibrary-1.0.4.dist-info/RECORD
